{"place_id":328022742,"licence":"Data © OpenStreetMap contributors, ODbL 1.0. https://osm.org/copyright","osm_type":"way","osm_id":553585445,"boundingbox":["42.733466909091","42.733566909091","-73.682332136364","-73.682232136364"],"lat":"42.73351690909091","lon":"-73.68228213636364","display_name":"41, 9th Street, Downtown, City of Troy, Rensselaer County, New York, 12180, United States","class":"place","type":"house","importance":-0.5399999999999999,"address":{"house_number":"41","road":"9th Street","neighbourhood":"Downtown","city":"City of Troy","county":"Rensselaer County","state":"New York","ISO3166-2-lvl4":"US-NY","postcode":"12180","country":"United States","country_code":"us"}}